__init__.py
ducttapedb/__init__.py
ducttapedb/autosafetytapedb/__init__.py
ducttapedb/autosafetytapedb/model.py
ducttapedb/ducttapedb/__init__.py
ducttapedb/ducttapedb/ducttapedb.py
ducttapedb/ducttapedb/ducttapemodel.py
ducttapedb/ducttapedb/validators.py
ducttapedb/hookloopdb/__init__.py
ducttapedb/hookloopdb/controller.py
ducttapedb/hookloopdb/model.py
ducttapedb/hookloopdb/table.py
ducttapedb/safetytapedb/__init__.py
ducttapedb/safetytapedb/model.py
ducttapedb/safetytapedb/table.py
ducttapedb-2025.2.19.1.dist-info/LICENSE
ducttapedb-2025.2.19.1.dist-info/METADATA
ducttapedb-2025.2.19.1.dist-info/WHEEL
ducttapedb-2025.2.19.1.dist-info/top_level.txt
ducttapedb-2025.2.19.1.dist-info/RECORD
