Metadata-Version: 2.2
Name: ducttapedb
Version: 2025.2.19.1
Summary: Persist pydantic models. Convenient model management and storage.
Author-email: Gabu <gaburyuu@gmail.com>
Maintainer-email: Gabu <gaburyuu@gmail.com>
License: MIT
Project-URL: Source, https://github.com/Gaburyuu/DuctTapeDB
Classifier: Development Status :: 4 - Beta
Classifier: Intended Audience :: Developers
Classifier: Topic :: Software Development :: Libraries
Classifier: License :: OSI Approved :: MIT License
Classifier: Programming Language :: Python :: 3.11
Classifier: Programming Language :: Python :: 3.12
Classifier: Programming Language :: Python :: 3.13
Classifier: Programming Language :: Python :: 3 :: Only
Requires-Python: >=3.11
License-File: LICENSE
Requires-Dist: pydantic>=2.0.0
Requires-Dist: aiosqlite
Provides-Extra: dev
Requires-Dist: pytest>=7.0.0; extra == "dev"
Requires-Dist: pytest-asyncio; extra == "dev"
Requires-Dist: pytest-benchmark; extra == "dev"
Requires-Dist: ruff; extra == "dev"
Requires-Dist: black; extra == "dev"
